splitup/__init__.py
splitup-1.0.5.dist-info/LICENSE.txt
splitup-1.0.5.dist-info/METADATA
splitup-1.0.5.dist-info/WHEEL
splitup-1.0.5.dist-info/top_level.txt
splitup-1.0.5.dist-info/RECORD
