Metadata-Version: 2.1
Name: splitup
Version: 1.0.5
Summary: Splitting files in a folder
Home-page: UNKNOWN
Author: Arvind R Menon
Author-email: arvind.ramesh.menon@gmail.com
License: UNKNOWN
Platform: UNKNOWN
Classifier: Programming Language :: Python :: 3
Classifier: License :: OSI Approved :: MIT License
Classifier: Operating System :: OS Independent
